ruuid-0.3.1.dist-info/METADATA
ruuid-0.3.1.dist-info/WHEEL
ruuid/__init__.py
ruuid/ruuid.abi3.so
ruuid-0.3.1.dist-info/RECORD
