Metadata-Version: 2.1
Name: ruuid
Version: 0.3.1
Summary: A fast UUID generator for Python using Rust
Keywords: uuid hash
Author: unrahul <rahulunair@gmail.com>
Author-Email: unrahul <rahulunair@gmail.com>
License: BSD-3-Clause
